CHANGES.rst
MANIFEST.in
README.rst
setup.py
django_viewset/__init__.py
django_viewset/mixins.py
django_viewset/utils.py
django_viewset/views.py
django_viewset/viewset.py
django_viewset.egg-info/PKG-INFO
django_viewset.egg-info/SOURCES.txt
django_viewset.egg-info/dependency_links.txt
django_viewset.egg-info/not-zip-safe
django_viewset.egg-info/top_level.txt
requirements/tests.txt
tests/__init__.py
tests/settings.py
tests/test_syntax.py
tests/test_viewset.py