Metadata-Version: 1.1
Name: django-viewset
Version: 0.1.1
Summary: A replacement of django.contrib.admin
Home-page: https://github.com/gregmuellegger/django-viewset
Author: Gregor Müllegger
Author-email: gregor@muellegger.de
License: BSD licence, see LICENSE file
Platform: UNKNOWN
Classifier: Development Status :: 3 - Alpha
Classifier: Environment :: Web Environment
Classifier: Framework :: Django
Classifier: Intended Audience :: Developers
Classifier: License :: OSI Approved :: BSD License
Classifier: Natural Language :: English
Classifier: Programming Language :: Python
Classifier: Programming Language :: Python :: 2
